<?xml version="1.0" ?>
<xpd>
    <dependency repo = "sc_i2c">
        <githash>86cb497a5ee519fbc0c4bb597adeeb135d3e97e1</githash>
        <uri>ssh://git@github.com/xcore/sc_i2c</uri>
        <version>2.0.0rc3</version>
    </dependency>
    <dependency repo = "xcommon">
        <githash>b7b5be59795a0a4b3fee4aeaff3c8e398bf76d27</githash>
        <uri>ssh://git@github.com/xcore/xcommon</uri>
        <version>1.0.0rc2</version>
    </dependency>
    <description>I2S Digital Audio Component</description>
    <docdir>doc</docdir>
    <location>git@github.com:xcore/sc_i2s</location>
    <name>sc_i2s</name>
    <maintainer>davelxmos</maintainer>
    <partnumber>XM-001654-DH</partnumber>
    <release parenthash = "7e3418fcb3ba55e96181913f28b412775cfa5937" version = "1.2.0beta0" githash = "1ef3ad83d50f361b49de59963192f7ef89af038f"></release>
    <release parenthash = "8add6ae72ee457b25ca8deaf6a02570706032e0c" version = "1.2.0rc0" githash = "237bf74edbe99636ee822c41b1fe7ddee1f141a7"></release>
    <release parenthash = "622160ca644b474415218a5050cdc135890ee1f5" version = "1.3.0rc0" githash = "a76a3cd3457181b92701239471918b1606a885a5"></release>
    <release parenthash = "08e0db677ffb3aee4b315d6b6468abd81465f6bf" version = "1.3.0rc1" githash = "f7b6a604107c4cac048a0f6d0a4bfa8cb0882020"></release>
    <scope>example</scope>
    <subpartnumber>XM-000076-SW</subpartnumber>
    <vendor>XMOS</vendor>
    <xpd_version>1.0</xpd_version>
</xpd>